joyreactor_stats/__init__.py
joyreactor_stats-1.1.2.dist-info/LICENSE
joyreactor_stats-1.1.2.dist-info/METADATA
joyreactor_stats-1.1.2.dist-info/WHEEL
joyreactor_stats-1.1.2.dist-info/top_level.txt
joyreactor_stats-1.1.2.dist-info/RECORD
